redshift_sqlalchemy/__init__.py
sqlalchemy_redshift/__init__.py
sqlalchemy_redshift/commands.py
sqlalchemy_redshift/ddl.py
sqlalchemy_redshift/dialect.py
sqlalchemy_redshift/redshift-ca-bundle.crt
sqlalchemy_redshift-0.8.13.dist-info/LICENSE
sqlalchemy_redshift-0.8.13.dist-info/METADATA
sqlalchemy_redshift-0.8.13.dist-info/WHEEL
sqlalchemy_redshift-0.8.13.dist-info/entry_points.txt
sqlalchemy_redshift-0.8.13.dist-info/top_level.txt
sqlalchemy_redshift-0.8.13.dist-info/RECORD
