Metadata-Version: 2.1
Name: sqlalchemy-redshift
Version: 0.8.13
Summary: Amazon Redshift Dialect for sqlalchemy
Home-page: https://github.com/sqlalchemy-redshift/sqlalchemy-redshift
Author: Matt George
Author-email: mgeorge@gmail.com
Maintainer: Thomas Grainger
Maintainer-email: sqlalchemy-redshift@graingert.co.uk
License: MIT
Classifier: Development Status :: 4 - Beta
Classifier: Environment :: Console
Classifier: Intended Audience :: Developers
Classifier: License :: OSI Approved :: MIT License
Classifier: Operating System :: OS Independent
Classifier: Programming Language :: Python
Classifier: Programming Language :: Python :: 3
Classifier: Programming Language :: Python :: 3.4
Classifier: Programming Language :: Python :: 3.5
Classifier: Programming Language :: Python :: 3.6
Classifier: Programming Language :: Python :: 3.7
Classifier: Programming Language :: Python :: 3.8
Classifier: Programming Language :: Python :: 3.9
Classifier: Programming Language :: Python :: 3.10
Requires-Python: >=3.4
License-File: LICENSE
Requires-Dist: SQLAlchemy (<2.0.0,>=0.9.2)
Requires-Dist: packaging
